lsverifier/__init__.py
lsverifier/analysis/__init__.py
lsverifier/analysis/analysis.py
lsverifier/bar/__init__.py
lsverifier/bar/bar.py
lsverifier/bin/esbmc
lsverifier/csvwr/__init__.py
lsverifier/csvwr/csvwr.py
lsverifier/log/__init__.py
lsverifier/log/log.py
lsverifier/utils/__init__.py
lsverifier/utils/shell.py
lsverifier/utils/utils.py
LSVerifier-0.3.0.dist-info/LICENSE
LSVerifier-0.3.0.dist-info/METADATA
LSVerifier-0.3.0.dist-info/WHEEL
LSVerifier-0.3.0.dist-info/entry_points.txt
LSVerifier-0.3.0.dist-info/top_level.txt
LSVerifier-0.3.0.dist-info/RECORD
