Metadata-Version: 2.1
Name: LSVerifier
Version: 0.3.0
Summary: This open-source tool streamlines software verification by allowing the simultaneous assessment of extensive files and functions in a single run. By leveraging the ESBMC module, it enhances vulnerability detection and reinforces software security.
Home-page: https://github.com/janislley/LSVerifier
Author: Thales Silva / Janislley Oliveira / Bruno Farias
Author-email: janislley@gmail.com
License: MIT
Classifier: License :: OSI Approved :: MIT License
Classifier: Programming Language :: Python
Classifier: Programming Language :: Python :: 3
Classifier: Programming Language :: Python :: 3.6
Classifier: Programming Language :: Python :: Implementation :: CPython
Classifier: Programming Language :: Python :: Implementation :: PyPy
Requires-Python: >=3.6.0
License-File: LICENSE
Requires-Dist: tqdm
